labman/__init__.py
labman/cli.py
labman/lib/audit.py
labman/lib/auth.py
labman/lib/content.py
labman/lib/data.py
labman/lib/email_queue.py
labman/lib/email_service.py
labman/lib/groups.py
labman/lib/helpers.py
labman/lib/inventory.py
labman/lib/meetings.py
labman/lib/research.py
labman/lib/servers.py
labman/lib/users.py
labman/server.py
labman/templates/activate_account.html
labman/templates/admin_reset_password.html
labman/templates/audit_history.html
labman/templates/base.html
labman/templates/change_password.html
labman/templates/content.html
labman/templates/content_form.html
labman/templates/dashboard.html
labman/templates/edit_profile.html
labman/templates/forgot_password.html
labman/templates/group_detail.html
labman/templates/group_form.html
labman/templates/groups.html
labman/templates/inventory.html
labman/templates/inventory_form.html
labman/templates/login.html
labman/templates/meeting_detail.html
labman/templates/meeting_form.html
labman/templates/meetings.html
labman/templates/member_research.html
labman/templates/research.html
labman/templates/reset_password.html
labman/templates/server_form.html
labman/templates/user_form.html
labman/templates/users.html
labman/tests/populate_test_data.py
labman/tests/test_email.py
ra_labman-0.2.0.dist-info/licenses/LICENSE
ra_labman-0.2.0.dist-info/WHEEL
ra_labman-0.2.0.dist-info/entry_points.txt
ra_labman-0.2.0.dist-info/METADATA
ra_labman-0.2.0.dist-info/RECORD
