Metadata-Version: 2.4
Name: ra-labMan
Version: 0.2.0
Summary: Academic Lab Management System
Author: Lokesh Mohanty
Author-email: Lokesh Mohanty <lokesh1197@gmail.com>
License-Expression: MIT
License-File: LICENSE
Classifier: Development Status :: 4 - Beta
Classifier: Environment :: Web Environment
Classifier: Framework :: Flask
Classifier: Intended Audience :: Education
Classifier: Intended Audience :: Science/Research
Classifier: License :: OSI Approved :: MIT License
Classifier: Operating System :: OS Independent
Classifier: Programming Language :: Python :: 3
Classifier: Programming Language :: Python :: 3.10
Classifier: Programming Language :: Python :: 3.11
Classifier: Programming Language :: Python :: 3.12
Classifier: Topic :: Scientific/Engineering
Classifier: Topic :: Scientific/Engineering :: Information Analysis
Requires-Dist: dotenv>=0.9.9
Requires-Dist: flask>=3.1.2
Requires-Dist: werkzeug>=3.1.5
Requires-Dist: click>=8.1.7
Requires-Dist: gunicorn>=23.0.0
Requires-Dist: python-crontab>=3.2.0
Requires-Python: >=3.10
Project-URL: Homepage, https://github.com/lokeshmohanty/labman
Project-URL: Issues, https://github.com/lokeshmohanty/labman/issues
Project-URL: Documentation, https://github.com/lokeshmohanty/labman/README.md
